<?xml version="1.0"?>
<instance>
	<info>
		<dataset>linear_single_price_limit</dataset>
		<name>67</name>
		<n>50</n>
		<m>1</m>
		<capacity>100</capacity>
	</info>
	<items>
		<item id="1" type="POLYNOMIAL" fixed_cost="-83.00" price_limit="100.00">
			<coefficients>
				<coefficient degree="0">169.01</coefficient>
				<coefficient degree="1">-0.89</coefficient>
			</coefficients>
		</item>
		<item id="2" type="POLYNOMIAL" fixed_cost="74.00" price_limit="100.00">
			<coefficients>
				<coefficient degree="0">1272.01</coefficient>
				<coefficient degree="1">-11.85</coefficient>
			</coefficients>
		</item>
		<item id="3" type="POLYNOMIAL" fixed_cost="28.00" price_limit="100.00">
			<coefficients>
				<coefficient degree="0">706.01</coefficient>
				<coefficient degree="1">-6.25</coefficient>
			</coefficients>
		</item>
		<item id="4" type="POLYNOMIAL" fixed_cost="-29.00" price_limit="100.00">
			<coefficients>
				<coefficient degree="0">136.01</coefficient>
				<coefficient degree="1">-0.81</coefficient>
			</coefficients>
		</item>
		<item id="5" type="POLYNOMIAL" fixed_cost="62.00" price_limit="100.00">
			<coefficients>
				<coefficient degree="0">1062.01</coefficient>
				<coefficient degree="1">-9.88</coefficient>
			</coefficients>
		</item>
		<item id="6" type="POLYNOMIAL" fixed_cost="-26.00" price_limit="100.00">
			<coefficients>
				<coefficient degree="0">1038.01</coefficient>
				<coefficient degree="1">-9.73</coefficient>
			</coefficients>
		</item>
		<item id="7" type="POLYNOMIAL" fixed_cost="76.00" price_limit="100.00">
			<coefficients>
				<coefficient degree="0">1364.01</coefficient>
				<coefficient degree="1">-13.23</coefficient>
			</coefficients>
		</item>
		<item id="8" type="POLYNOMIAL" fixed_cost="-57.00" price_limit="100.00">
			<coefficients>
				<coefficient degree="0">65.01</coefficient>
				<coefficient degree="1">-0.29</coefficient>
			</coefficients>
		</item>
		<item id="9" type="POLYNOMIAL" fixed_cost="-77.00" price_limit="100.00">
			<coefficients>
				<coefficient degree="0">1427.01</coefficient>
				<coefficient degree="1">-13.90</coefficient>
			</coefficients>
		</item>
		<item id="10" type="POLYNOMIAL" fixed_cost="-26.00" price_limit="100.00">
			<coefficients>
				<coefficient degree="0">461.01</coefficient>
				<coefficient degree="1">-3.77</coefficient>
			</coefficients>
		</item>
		<item id="11" type="POLYNOMIAL" fixed_cost="20.00" price_limit="100.00">
			<coefficients>
				<coefficient degree="0">262.01</coefficient>
				<coefficient degree="1">-1.74</coefficient>
			</coefficients>
		</item>
		<item id="12" type="POLYNOMIAL" fixed_cost="88.00" price_limit="100.00">
			<coefficients>
				<coefficient degree="0">390.01</coefficient>
				<coefficient degree="1">-3.38</coefficient>
			</coefficients>
		</item>
		<item id="13" type="POLYNOMIAL" fixed_cost="-67.00" price_limit="100.00">
			<coefficients>
				<coefficient degree="0">178.01</coefficient>
				<coefficient degree="1">-1.14</coefficient>
			</coefficients>
		</item>
		<item id="14" type="POLYNOMIAL" fixed_cost="-93.00" price_limit="100.00">
			<coefficients>
				<coefficient degree="0">357.01</coefficient>
				<coefficient degree="1">-3.00</coefficient>
			</coefficients>
		</item>
		<item id="15" type="POLYNOMIAL" fixed_cost="1.00" price_limit="100.00">
			<coefficients>
				<coefficient degree="0">1435.01</coefficient>
				<coefficient degree="1">-13.93</coefficient>
			</coefficients>
		</item>
		<item id="16" type="POLYNOMIAL" fixed_cost="31.00" price_limit="100.00">
			<coefficients>
				<coefficient degree="0">1870.01</coefficient>
				<coefficient degree="1">-17.87</coefficient>
			</coefficients>
		</item>
		<item id="17" type="POLYNOMIAL" fixed_cost="92.00" price_limit="100.00">
			<coefficients>
				<coefficient degree="0">2001.01</coefficient>
				<coefficient degree="1">-19.22</coefficient>
			</coefficients>
		</item>
		<item id="18" type="POLYNOMIAL" fixed_cost="4.00" price_limit="100.00">
			<coefficients>
				<coefficient degree="0">1979.01</coefficient>
				<coefficient degree="1">-18.99</coefficient>
			</coefficients>
		</item>
		<item id="19" type="POLYNOMIAL" fixed_cost="50.00" price_limit="100.00">
			<coefficients>
				<coefficient degree="0">1239.01</coefficient>
				<coefficient degree="1">-12.19</coefficient>
			</coefficients>
		</item>
		<item id="20" type="POLYNOMIAL" fixed_cost="11.00" price_limit="100.00">
			<coefficients>
				<coefficient degree="0">1406.01</coefficient>
				<coefficient degree="1">-13.68</coefficient>
			</coefficients>
		</item>
		<item id="21" type="POLYNOMIAL" fixed_cost="-61.00" price_limit="100.00">
			<coefficients>
				<coefficient degree="0">1180.01</coefficient>
				<coefficient degree="1">-11.52</coefficient>
			</coefficients>
		</item>
		<item id="22" type="POLYNOMIAL" fixed_cost="-80.00" price_limit="100.00">
			<coefficients>
				<coefficient degree="0">1386.01</coefficient>
				<coefficient degree="1">-13.42</coefficient>
			</coefficients>
		</item>
		<item id="23" type="POLYNOMIAL" fixed_cost="-74.00" price_limit="100.00">
			<coefficients>
				<coefficient degree="0">824.01</coefficient>
				<coefficient degree="1">-8.04</coefficient>
			</coefficients>
		</item>
		<item id="24" type="POLYNOMIAL" fixed_cost="14.00" price_limit="100.00">
			<coefficients>
				<coefficient degree="0">1154.01</coefficient>
				<coefficient degree="1">-11.29</coefficient>
			</coefficients>
		</item>
		<item id="25" type="POLYNOMIAL" fixed_cost="66.00" price_limit="100.00">
			<coefficients>
				<coefficient degree="0">447.01</coefficient>
				<coefficient degree="1">-4.18</coefficient>
			</coefficients>
		</item>
		<item id="26" type="POLYNOMIAL" fixed_cost="-66.00" price_limit="100.00">
			<coefficients>
				<coefficient degree="0">1763.01</coefficient>
				<coefficient degree="1">-16.82</coefficient>
			</coefficients>
		</item>
		<item id="27" type="POLYNOMIAL" fixed_cost="-73.00" price_limit="100.00">
			<coefficients>
				<coefficient degree="0">957.01</coefficient>
				<coefficient degree="1">-8.65</coefficient>
			</coefficients>
		</item>
		<item id="28" type="POLYNOMIAL" fixed_cost="-58.00" price_limit="100.00">
			<coefficients>
				<coefficient degree="0">228.01</coefficient>
				<coefficient degree="1">-2.02</coefficient>
			</coefficients>
		</item>
		<item id="29" type="POLYNOMIAL" fixed_cost="16.00" price_limit="100.00">
			<coefficients>
				<coefficient degree="0">1052.01</coefficient>
				<coefficient degree="1">-10.23</coefficient>
			</coefficients>
		</item>
		<item id="30" type="POLYNOMIAL" fixed_cost="61.00" price_limit="100.00">
			<coefficients>
				<coefficient degree="0">1220.01</coefficient>
				<coefficient degree="1">-11.99</coefficient>
			</coefficients>
		</item>
		<item id="31" type="POLYNOMIAL" fixed_cost="-90.00" price_limit="100.00">
			<coefficients>
				<coefficient degree="0">842.01</coefficient>
				<coefficient degree="1">-7.99</coefficient>
			</coefficients>
		</item>
		<item id="32" type="POLYNOMIAL" fixed_cost="14.00" price_limit="100.00">
			<coefficients>
				<coefficient degree="0">1786.01</coefficient>
				<coefficient degree="1">-17.44</coefficient>
			</coefficients>
		</item>
		<item id="33" type="POLYNOMIAL" fixed_cost="25.00" price_limit="100.00">
			<coefficients>
				<coefficient degree="0">534.01</coefficient>
				<coefficient degree="1">-4.52</coefficient>
			</coefficients>
		</item>
		<item id="34" type="POLYNOMIAL" fixed_cost="77.00" price_limit="100.00">
			<coefficients>
				<coefficient degree="0">1989.01</coefficient>
				<coefficient degree="1">-19.00</coefficient>
			</coefficients>
		</item>
		<item id="35" type="POLYNOMIAL" fixed_cost="-29.00" price_limit="100.00">
			<coefficients>
				<coefficient degree="0">524.01</coefficient>
				<coefficient degree="1">-4.28</coefficient>
			</coefficients>
		</item>
		<item id="36" type="POLYNOMIAL" fixed_cost="63.00" price_limit="100.00">
			<coefficients>
				<coefficient degree="0">1584.01</coefficient>
				<coefficient degree="1">-15.57</coefficient>
			</coefficients>
		</item>
		<item id="37" type="POLYNOMIAL" fixed_cost="-10.00" price_limit="100.00">
			<coefficients>
				<coefficient degree="0">121.01</coefficient>
				<coefficient degree="1">-0.60</coefficient>
			</coefficients>
		</item>
		<item id="38" type="POLYNOMIAL" fixed_cost="78.00" price_limit="100.00">
			<coefficients>
				<coefficient degree="0">1603.01</coefficient>
				<coefficient degree="1">-15.37</coefficient>
			</coefficients>
		</item>
		<item id="39" type="POLYNOMIAL" fixed_cost="69.00" price_limit="100.00">
			<coefficients>
				<coefficient degree="0">157.01</coefficient>
				<coefficient degree="1">-1.29</coefficient>
			</coefficients>
		</item>
		<item id="40" type="POLYNOMIAL" fixed_cost="68.00" price_limit="100.00">
			<coefficients>
				<coefficient degree="0">1235.01</coefficient>
				<coefficient degree="1">-11.99</coefficient>
			</coefficients>
		</item>
		<item id="41" type="POLYNOMIAL" fixed_cost="-32.00" price_limit="100.00">
			<coefficients>
				<coefficient degree="0">328.01</coefficient>
				<coefficient degree="1">-2.87</coefficient>
			</coefficients>
		</item>
		<item id="42" type="POLYNOMIAL" fixed_cost="-35.00" price_limit="100.00">
			<coefficients>
				<coefficient degree="0">869.01</coefficient>
				<coefficient degree="1">-8.30</coefficient>
			</coefficients>
		</item>
		<item id="43" type="POLYNOMIAL" fixed_cost="-76.00" price_limit="100.00">
			<coefficients>
				<coefficient degree="0">811.01</coefficient>
				<coefficient degree="1">-7.64</coefficient>
			</coefficients>
		</item>
		<item id="44" type="POLYNOMIAL" fixed_cost="41.00" price_limit="100.00">
			<coefficients>
				<coefficient degree="0">1199.01</coefficient>
				<coefficient degree="1">-11.59</coefficient>
			</coefficients>
		</item>
		<item id="45" type="POLYNOMIAL" fixed_cost="98.00" price_limit="100.00">
			<coefficients>
				<coefficient degree="0">1231.01</coefficient>
				<coefficient degree="1">-11.77</coefficient>
			</coefficients>
		</item>
		<item id="46" type="POLYNOMIAL" fixed_cost="-67.00" price_limit="100.00">
			<coefficients>
				<coefficient degree="0">863.01</coefficient>
				<coefficient degree="1">-7.94</coefficient>
			</coefficients>
		</item>
		<item id="47" type="POLYNOMIAL" fixed_cost="-13.00" price_limit="100.00">
			<coefficients>
				<coefficient degree="0">758.01</coefficient>
				<coefficient degree="1">-7.01</coefficient>
			</coefficients>
		</item>
		<item id="48" type="POLYNOMIAL" fixed_cost="-45.00" price_limit="100.00">
			<coefficients>
				<coefficient degree="0">1847.01</coefficient>
				<coefficient degree="1">-17.68</coefficient>
			</coefficients>
		</item>
		<item id="49" type="POLYNOMIAL" fixed_cost="69.00" price_limit="100.00">
			<coefficients>
				<coefficient degree="0">1995.01</coefficient>
				<coefficient degree="1">-19.65</coefficient>
			</coefficients>
		</item>
		<item id="50" type="POLYNOMIAL" fixed_cost="-84.00" price_limit="100.00">
			<coefficients>
				<coefficient degree="0">712.01</coefficient>
				<coefficient degree="1">-6.37</coefficient>
			</coefficients>
		</item>
	</items>
</instance>
